Metadata-Version: 2.4
Name: mcp-servers-auto-test
Version: 0.2.2
Summary: MCP Servers Automated Testing Application - Test MCP servers with ease
Author-email: xray918 <xray918@example.com>
License: MIT
License-File: LICENSE
Keywords: automation,mcp,model-context-protocol,servers,testing
Classifier: Development Status :: 4 - Beta
Classifier: Intended Audience :: Developers
Classifier: License :: OSI Approved :: MIT License
Classifier: Programming Language :: Python :: 3
Classifier: Programming Language :: Python :: 3.10
Classifier: Programming Language :: Python :: 3.11
Classifier: Programming Language :: Python :: 3.12
Classifier: Topic :: Software Development :: Libraries :: Python Modules
Classifier: Topic :: Software Development :: Testing
Requires-Python: >=3.10
Requires-Dist: aiohttp>=3.9.0
Requires-Dist: colorama>=0.4.6
Requires-Dist: mcp>=1.1.2
Requires-Dist: motor>=3.3.0
Requires-Dist: openai>=1.0.0
Requires-Dist: pydantic>=2.0.0
Requires-Dist: pymongo>=4.0.0
Requires-Dist: python-dotenv>=1.0.0
Requires-Dist: tabulate>=0.9.0
